{
    "districts": [
        {
            "name": "ПОЛИТЕХНИЧЕСКИЙ\nРАЙОН",
            "points": [
                [-251, 8, -693],
                [-1100, 8, -693],
                [-1100, 8, -1700],
                [-251, 8, -1700]
            ]
        },
        {
            "name": "ЦЕНТРАЛЬНЫЙ\nРАЙОН",
            "points": [
                [-251, 8, -693],
                [-1100, 8, -693],
                [-1100, 8, 550],
                [-251, 8, 550]
            ]
        },
        {
            "name": "ЖЕЛЕЗНОДОРОЖНЫЙ\nРАЙОН",
            "points": [
                [-251, 8, -1400],
                [-251, 8, -40],
                [1500, 8, -40],
                [1500, 8, -1400]
            ]
        }
    ]
}